dr_simulator/__init__.py
dr_simulator/costs.py
dr_simulator/data.py
dr_simulator/dr_events.py
dr_simulator/utils.py
dr_simulator/visulization_helper.py
dr_simulator-0.4.0.dist-info/LICENSE
dr_simulator-0.4.0.dist-info/METADATA
dr_simulator-0.4.0.dist-info/WHEEL
dr_simulator-0.4.0.dist-info/RECORD
