Metadata-Version: 2.3
Name: dr-simulator
Version: 0.4.0
Summary: Demand Response Simulator enables you to sample DR events based on a distribution and optimize your energy flexible process
License: MIT
Keywords: demand-response,simulator,energy,forecasting,optimization
Author: ThyanRevolter
Author-email: admkr.2010@gmail.com
Requires-Python: >=3.9,<3.12
Classifier: Development Status :: 3 - Alpha
Classifier: Intended Audience :: Education
Classifier: Intended Audience :: Science/Research
Classifier: License :: OSI Approved :: MIT License
Classifier: Natural Language :: English
Classifier: Programming Language :: Python :: 3
Classifier: Programming Language :: Python :: 3.9
Classifier: Programming Language :: Python :: 3.10
Classifier: Programming Language :: Python :: 3.11
Requires-Dist: Sphinx (>=4.2.0)
Requires-Dist: black (>=21.12b0)
Requires-Dist: bumpver (>=2023.1129,<2024.0)
Requires-Dist: cvxpy (>=1.4.1)
Requires-Dist: holidays (>=0.41)
Requires-Dist: ipykernel
Requires-Dist: marimo (>=0.3.2)
Requires-Dist: matplotlib (>=3.2.2)
Requires-Dist: numpy (<2.0)
Requires-Dist: pandas (>=2.2.1)
Requires-Dist: pylance (>=0.9.15)
Requires-Dist: pylint (>=3.0.3,<4.0.0)
Requires-Dist: pytest (>=7.4.4,<8.0.0)
Requires-Dist: pytest-cov (>=4.1.0,<5.0.0)
Requires-Dist: pytest-html (>=3.0.0)
Requires-Dist: scipy (>=1.8.0)
Requires-Dist: setuptools (>=69.1.1,<70.0.0)
Requires-Dist: sphinx-rtd-theme (>=2.0.0,<3.0.0)
Requires-Dist: tox (>=4.14.1,<5.0.0)
Project-URL: Documentation, https://we3lab.github.io/dr-simulator/index.html
Project-URL: Homepage, https://github.com/we3lab/dr-simulator
Project-URL: Repository, https://github.com/we3lab/dr-simulator
